orkz/__about__.py
orkz/__init__.py
orkz-0.0.1.dist-info/METADATA
orkz-0.0.1.dist-info/WHEEL
orkz-0.0.1.dist-info/licenses/LICENSE.txt
orkz-0.0.1.dist-info/RECORD
